face_engine/__init__.py
face_engine/core.py
face_engine/exceptions.py
face_engine/fetching.py
face_engine/tools.py
face_engine/models/__init__.py
face_engine/models/basic_estimator.py
face_engine/models/dlib_models.py
face_engine/models/insightface_models.py
face_engine-2.1.0.dist-info/LICENSE
face_engine-2.1.0.dist-info/METADATA
face_engine-2.1.0.dist-info/WHEEL
face_engine-2.1.0.dist-info/top_level.txt
face_engine-2.1.0.dist-info/RECORD
