Metadata-Version: 2.1
Name: face-engine
Version: 2.1.0
Summary: Face Recognition Engine
Home-page: https://github.com/guesswh0/face_engine
Author: Daniyar Kussainov
Author-email: ohw0sseug@gmail.com
License: Apache License, Version 2.0
Platform: UNKNOWN
Classifier: License :: OSI Approved :: Apache Software License
Classifier: Natural Language :: English
Classifier: Intended Audience :: Developers
Classifier: Intended Audience :: Education
Classifier: Topic :: Scientific/Engineering :: Image Recognition
Classifier: Operating System :: OS Independent
Classifier: Programming Language :: Python :: 3
Classifier: Programming Language :: Python :: 3.6
Classifier: Programming Language :: Python :: 3.7
Classifier: Programming Language :: Python :: 3.8
Classifier: Programming Language :: Python :: 3 :: Only
Requires-Python: >=3.6
License-File: LICENSE
Requires-Dist: numpy (<2.0,>=1.18.0)
Requires-Dist: pillow (<9.0,>=8.0.0)
Requires-Dist: tqdm (<5.0,>=4.44.0)
Provides-Extra: dev
Requires-Dist: dlib ; extra == 'dev'
Requires-Dist: opencv-python-headless ; extra == 'dev'
Requires-Dist: sphinx ; extra == 'dev'
Requires-Dist: sphinx-rtd-theme ; extra == 'dev'
